async_covid/__init__.py
async_covid/config.py
async_covid/john_hopkins/__init__.py
async_covid/john_hopkins/covid.py
async_covid/john_hopkins/models.py
async_covid/worldometers/__init__.py
async_covid/worldometers/covid.py
async_covid/worldometers/models.py
async_covid-0.0.11.dist-info/LICENSE.txt
async_covid-0.0.11.dist-info/METADATA
async_covid-0.0.11.dist-info/WHEEL
async_covid-0.0.11.dist-info/top_level.txt
async_covid-0.0.11.dist-info/RECORD
