Metadata-Version: 2.1
Name: async-covid
Version: 0.0.11
Summary: An async Python package to get information regarding the novel corona virus provided by Johns Hopkins university and worldometers.info. Based on https://github.com/ahmednafies/covid
Home-page: UNKNOWN
Author: K.M Ahnaf Zail
Author-email: ahnafzamil@protonmail.com
License: MIT
Project-URL: Source, https://github.com/ahnaf-zamil/async-covid
Platform: UNKNOWN
Classifier: Intended Audience :: Developers
Classifier: Topic :: Utilities
Classifier: License :: OSI Approved :: MIT License
Classifier: Programming Language :: Python :: 3
Classifier: Programming Language :: Python :: 3.7
Classifier: Programming Language :: Python :: 3.8
Requires-Python: >=3.6
Requires-Dist: aiohttp
Requires-Dist: asyncio
Requires-Dist: beautifulsoup4
Requires-Dist: pydantic
Requires-Dist: typer
Provides-Extra: dev
Requires-Dist: black ; extra == 'dev'
Requires-Dist: coverage ; extra == 'dev'
Requires-Dist: flake8 ; extra == 'dev'
Requires-Dist: ipdb ; extra == 'dev'
Requires-Dist: pipenv ; extra == 'dev'
Requires-Dist: pre-commit ; extra == 'dev'
Requires-Dist: pytest ; extra == 'dev'
